mpl_qt_viz/__init__.py
mpl_qt_viz/__main__.py
mpl_qt_viz/version.py
mpl_qt_viz/roiSelection/__init__.py
mpl_qt_viz/roiSelection/_coreClasses.py
mpl_qt_viz/roiSelection/_creatorWidgets/FullImPaintSelector.py
mpl_qt_viz/roiSelection/_creatorWidgets/WaterShedPaintSelector.py
mpl_qt_viz/roiSelection/_creatorWidgets/__init__.py
mpl_qt_viz/roiSelection/_creatorWidgets/_base.py
mpl_qt_viz/roiSelection/_creatorWidgets/_segmentation.py
mpl_qt_viz/roiSelection/_creatorWidgets/_sharedWidgets.py
mpl_qt_viz/roiSelection/_creatorWidgets/ellipse.py
mpl_qt_viz/roiSelection/_creatorWidgets/lasso.py
mpl_qt_viz/roiSelection/_creatorWidgets/paint.py
mpl_qt_viz/roiSelection/_creatorWidgets/point.py
mpl_qt_viz/roiSelection/_creatorWidgets/square.py
mpl_qt_viz/roiSelection/_modifierWidgets/__init__.py
mpl_qt_viz/roiSelection/_modifierWidgets/_base.py
mpl_qt_viz/roiSelection/_modifierWidgets/movingModifier.py
mpl_qt_viz/roiSelection/_modifierWidgets/polygonModifier.py
mpl_qt_viz/roiSelection/_utilityClasses/__init__.py
mpl_qt_viz/roiSelection/_utilityClasses/adjustableSelector.py
mpl_qt_viz/visualizers/__init__.py
mpl_qt_viz/visualizers/_multiPlot.py
mpl_qt_viz/visualizers/_sharedWidgets.py
mpl_qt_viz/visualizers/_PlotNd/__init__.py
mpl_qt_viz/visualizers/_PlotNd/_canvas.py
mpl_qt_viz/visualizers/_PlotNd/_plots.py
mpl_qt_viz/visualizers/_dockPlot/__init__.py
mpl_qt_viz-1.1.0.dist-info/COPYING
mpl_qt_viz-1.1.0.dist-info/METADATA
mpl_qt_viz-1.1.0.dist-info/WHEEL
mpl_qt_viz-1.1.0.dist-info/top_level.txt
mpl_qt_viz-1.1.0.dist-info/RECORD
