Metadata-Version: 2.2
Name: mpl_qt_viz
Version: 1.1.0
Summary: A Python package providing enhanced data visualization and ROI selection built on top of Matplotlib and PyQt6.
Home-page: https://github.com/nanthony21/mpl_qt_viz
Author: Nick Anthony
Author-email: nickmanthony@hotmail.com
Requires-Python: >=3.7
License-File: COPYING
Requires-Dist: numpy
Requires-Dist: scipy
Requires-Dist: matplotlib
Requires-Dist: shapely
Requires-Dist: PyQt6
Requires-Dist: scikit-image
Requires-Dist: opencv-python
Requires-Dist: cycler
Dynamic: author
Dynamic: author-email
Dynamic: description
Dynamic: description-content-type
Dynamic: home-page
Dynamic: requires-dist
Dynamic: requires-python
Dynamic: summary
